drf_tester/__init__.py
drf_tester/utils.py
drf_tester/viewsets/__init__.py
drf_tester/viewsets/admin.py
drf_tester/viewsets/anon.py
drf_tester/viewsets/auth.py
drf_tester/viewsets/staff.py
drf_tester-0.1.2.dist-info/LICENSE.md
drf_tester-0.1.2.dist-info/METADATA
drf_tester-0.1.2.dist-info/WHEEL
drf_tester-0.1.2.dist-info/top_level.txt
drf_tester-0.1.2.dist-info/RECORD
