Metadata-Version: 2.1
Name: drf-tester
Version: 0.1.2
Summary: Testing Suite for DjangoRestFramework developers with deadlines.
Home-page: http://github.com/samuelmovi/drf-tester/
Author: Samuel Movi
Author-email: samuel.software.developer@email.com
License: MIT
Platform: UNKNOWN
Requires-Python: >=3.6
License-File: LICENSE.md
Requires-Dist: Django
Requires-Dist: djangorestframework
